{
    "id": 3,
    "name": "Sentiments printaniers",
    "availableStock": 1,
    "skin": "Propre, fra\u00eeche",
    "aromas": "Frais et fruit\u00e9",
    "ingredients": "Framboise, zeste de citron et feuille de menthe",
    "description": "Savon avec une formule douce \u00e0 base d\u2019huile de framboise, de citron et de menthe qui nettoie les mains efficacement sans les dess\u00e9cher.",
    "price": 60,
    "picture": "https:\/\/cdn.pixabay.com\/photo\/2020\/02\/08\/10\/35\/soap-4829708_960_720.jpg",
    "varieties": 4
}